<!DOCTYPE generatorConfiguration PUBLIC
        "-//mybatis.org//DTD MyBatis Generator Configuration 1.0//EN"
        "http://mybatis.org/dtd/mybatis-generator-config_1_0.dtd">
<generatorConfiguration>
    <context id="dsql" targetRuntime="MyBatis3">
<!--    <context id="dsql" targetRuntime="MyBatis3DynamicSql">-->

    <commentGenerator >
            <property name="dateFormat" value="yyyy-mm-dd HH:mm:ss"/>
            <property name="suppressAllComments" value="true"/>
        </commentGenerator>
        <jdbcConnection driverClass="com.mysql.cj.jdbc.Driver"
                        userId="root"
                        password="Aa123456."
                        connectionURL="jdbc:mysql://localhost/shop" />
        <javaTypeResolver>
            <property name="forceBigDecimals" value="true"/>
            <!-- This property is used to specify whether MyBatis Generator should force the use of JSR-310 data types for DATE, TIME,
            and TIMESTAMP fields, rather than using java.util.Date -->
            <property name="useJSR310Types" value="true"/>
        </javaTypeResolver>
        <javaModelGenerator targetPackage="org.shop.model.dao" targetProject="mybatis-generator/src/main/java"/>
        <sqlMapGenerator targetPackage="org.shop.mapper" targetProject="mybatis-generator/src/main/resources"/>

        <javaClientGenerator type="XMLMAPPER" targetPackage="org.shop.mapper" targetProject="mybatis-generator/src/main/java"/>
<!--        <table tableName="cart_item" domainObjectName="CartItemDAO" ></table>-->
<!--        <table tableName="customer" domainObjectName="CustomerDAO" ></table>-->
<!--        <table tableName="customer_address" domainObjectName="CustomerAddressDAO"></table>-->
<!--        <table tableName="image" domainObjectName="ImageDAO"></table>-->
<!--        <table tableName="image_product" domainObjectName="ImageProductDAO"></table>-->
<!--        <table tableName="order_item" domainObjectName="OrderItemDAO" />-->
<!--        <table tableName="product" domainObjectName="ProductDAO"></table>-->
<!--        <table tableName="shop_order" domainObjectName="ShopOrderDAO"/>-->
<!--        <table tableName="shopping_cart" domainObjectName="ShoppingCartDAO"></table>-->
<!--        <table tableName="snapshot_product" domainObjectName="SnapshotProductDAO"></table>-->
<!--        <table tableName="brand" domainObjectName="BrandDAO"></table>-->
<!--        <table tableName="sku" domainObjectName="SkuDAO">-->
<!--            <generatedKey column="id" sqlStatement="MySql"></generatedKey>-->
<!--        </table>-->
<!--        <table tableName="attr_key" domainObjectName="AttrKeyDAO"></table>-->
<!--        <table tableName="attr_value" domainObjectName="AttrValueDAO"></table>-->
        <table tableName="category"  domainObjectName="CategoryDAO">
            <generatedKey column="id" sqlStatement="MySql"></generatedKey>
        </table>
    </context>
</generatorConfiguration>